README.md
setup.cfg
setup.py
bin/pyjst
pyjst/__init__.py
pyjst.egg-info/PKG-INFO
pyjst.egg-info/SOURCES.txt
pyjst.egg-info/dependency_links.txt
pyjst.egg-info/not-zip-safe
pyjst.egg-info/requires.txt
pyjst.egg-info/top_level.txt