Metadata-Version: 1.0
Name: pyjst
Version: 0.1.1
Summary: Bake a template from corresponding JSON object
Home-page: http://github.com/GuillaumeDesforges/pyjst
Author: Guillaume Desforges
Author-email: aceus02@gmail.com
License: MIT
Keywords: simple static template templating json
Platform: UNKNOWN
